gsheets_plaid/__init__.py
gsheets_plaid/__main__.py
gsheets_plaid/create_sheet.py
gsheets_plaid/services.py
gsheets_plaid/sync.py
gsheets_plaid/web_server/__init__.py
gsheets_plaid/web_server/main.py
gsheets_plaid/web_server/session_manager.py
gsheets_plaid/web_server/static/plaid_link.js
gsheets_plaid/web_server/templates/checklist.html
gsheets_plaid/web_server/templates/google_spreadsheet_form.html
gsheets_plaid/web_server/templates/index.html
gsheets_plaid/web_server/templates/login.html
gsheets_plaid/web_server/templates/plaid_credentials_form.html
gsheets_plaid/web_server/templates/plaid_items_form.html
gsheets_plaid-0.4.3.dist-info/LICENSE
gsheets_plaid-0.4.3.dist-info/METADATA
gsheets_plaid-0.4.3.dist-info/WHEEL
gsheets_plaid-0.4.3.dist-info/top_level.txt
gsheets_plaid-0.4.3.dist-info/RECORD
