Metadata-Version: 2.1
Name: gsheets-plaid
Version: 0.4.3
Summary: Tool for syncing bank transaction data to Google Sheets with Plaid.
Home-page: https://github.com/evanphilipsmith/gsheets-plaid
Author: Evan Smith
Author-email: evanphilipsmith@gmail.com
Project-URL: Bug Tracker, https://github.com/evanphilipsmith/gsheets-plaid/issues
Keywords: google sheets gsheets plaid transactions banking
Classifier: Development Status :: 3 - Alpha
Classifier: Intended Audience :: Developers
Classifier: License :: OSI Approved :: GNU General Public License v3 (GPLv3)
Classifier: Operating System :: MacOS
Classifier: Programming Language :: Python :: 3.10
Classifier: Topic :: Database
Classifier: Topic :: Office/Business :: Financial
Classifier: Topic :: Office/Business :: Financial :: Spreadsheet
Classifier: Topic :: Utilities
Requires-Python: >=3.10
License-File: LICENSE
Requires-Dist: google-api-python-client
Requires-Dist: google-auth-httplib2
Requires-Dist: google-auth-oauthlib
Requires-Dist: pandas
Requires-Dist: plaid-python
Requires-Dist: python-dotenv
Requires-Dist: flask
Requires-Dist: google-cloud-firestore
Requires-Dist: google-cloud-secret-manager
Requires-Dist: cryptography
